__init__.py
crypto.py
decrypter.py
file_io.py
qt.py
settings.py
storage.py
tdf.py
telegram_tdata_decrypter/__init__.py
telegram_tdata_decrypter/crypto.py
telegram_tdata_decrypter/decrypter.py
telegram_tdata_decrypter/file_io.py
telegram_tdata_decrypter/qt.py
telegram_tdata_decrypter/settings.py
telegram_tdata_decrypter/storage.py
telegram_tdata_decrypter/tdf.py
telegram_tdata_decrypter-1.1.2.dist-info/METADATA
telegram_tdata_decrypter-1.1.2.dist-info/WHEEL
telegram_tdata_decrypter-1.1.2.dist-info/top_level.txt
telegram_tdata_decrypter-1.1.2.dist-info/RECORD
