Metadata-Version: 2.1
Name: telegram_tdata_decrypter
Version: 1.1.2
Summary: decrypter tdata to session
Author: small_shushu
Requires-Python: >=3.7, <4
Requires-Dist: tgcrypto
